aligo/__init__.py
aligo/apis/Album.py
aligo/apis/Aligo.py
aligo/apis/Audio.py
aligo/apis/Compress.py
aligo/apis/Copy.py
aligo/apis/Create.py
aligo/apis/CustomShare.py
aligo/apis/Download.py
aligo/apis/Drive.py
aligo/apis/Duplicate.py
aligo/apis/File.py
aligo/apis/Move.py
aligo/apis/Other.py
aligo/apis/Recyclebin.py
aligo/apis/Search.py
aligo/apis/Share.py
aligo/apis/Star.py
aligo/apis/SyncFolder.py
aligo/apis/Update.py
aligo/apis/Video.py
aligo/apis/__init__.py
aligo/core/Album.py
aligo/core/Audio.py
aligo/core/Auth.py
aligo/core/BaseAligo.py
aligo/core/Compress.py
aligo/core/Config.py
aligo/core/Copy.py
aligo/core/Core.py
aligo/core/Create.py
aligo/core/Download.py
aligo/core/Drive.py
aligo/core/Duplicate.py
aligo/core/EMail.py
aligo/core/File.py
aligo/core/LoginServer.py
aligo/core/Move.py
aligo/core/Other.py
aligo/core/Recyclebin.py
aligo/core/SBox.py
aligo/core/Search.py
aligo/core/Share.py
aligo/core/Star.py
aligo/core/Template.py
aligo/core/Update.py
aligo/core/User.py
aligo/core/Video.py
aligo/core/__init__.py
aligo/error/__init__.py
aligo/request/AimSearchRequest.py
aligo/request/AlbumListFilesRequest.py
aligo/request/AlbumListRequest.py
aligo/request/ArchiveStatusRequest.py
aligo/request/ArchiveUncompressRequest.py
aligo/request/BatchCancelShareRequest.py
aligo/request/BatchCopyFilesRequest.py
aligo/request/BatchDownloadUrlRequest.py
aligo/request/BatchGetFileRequest.py
aligo/request/BatchMoveFilesRequest.py
aligo/request/BatchMoveToTrashRequest.py
aligo/request/BatchRequest.py
aligo/request/BatchRestoreRequest.py
aligo/request/BatchShareFileSaveToDriveRequest.py
aligo/request/BatchStarFilesRequest.py
aligo/request/BatchSubRequest.py
aligo/request/CancelShareLinkRequest.py
aligo/request/CompleteFileRequest.py
aligo/request/CopyFileRequest.py
aligo/request/CreateFileRequest.py
aligo/request/CreateFolderRequest.py
aligo/request/CreateShareLinkRequest.py
aligo/request/GetAudioPlayInfoRequest.py
aligo/request/GetDefaultDriveRequest.py
aligo-6.2.8.dist-info/licenses/LICENSE
aligo-6.2.8.dist-info/METADATA
aligo-6.2.8.dist-info/WHEEL
aligo-6.2.8.dist-info/top_level.txt
aligo-6.2.8.dist-info/RECORD
