Metadata-Version: 2.4
Name: aligo
Version: 6.2.8
Summary: aliyun drive sdk
Author: foyoux
Project-URL: Source, https://github.com/foyoux/aligo
Project-URL: Homepage, https://github.com/foyoux/aligo
Project-URL: Bug Tracker, https://github.com/foyoux/aligo/issues
Keywords: aligo
Classifier: Programming Language :: Python
Classifier: Programming Language :: Python :: 3
Classifier: Programming Language :: Python :: 3.7
Classifier: Programming Language :: Python :: 3.8
Classifier: Programming Language :: Python :: 3.9
Classifier: Programming Language :: Python :: 3.10
Classifier: Programming Language :: Python :: 3.11
Requires-Python: >=3.7
License-File: LICENSE
Requires-Dist: datclass>=0.2.22
Requires-Dist: requests>=2.9.0
Requires-Dist: qrcode[pil]
Requires-Dist: coloredlogs
Requires-Dist: tqdm>=4.50.0
Requires-Dist: qrcode_terminal
Dynamic: license-file
